{
  "clients": [
    {
      "name": "Jose Miguel",
      "company": "JA Asoc",
      "email": "leonelpolanco2913@gmail.com",
      "phone": "3122215315",
      "notes": "Notes..",
      "id": 1
    },
    {
      "name": "Diana Cristina",
      "company": "Meta",
      "email": "diana913@gmail.com",
      "phone": "3122215315",
      "notes": "Notes...",
      "id": 2
    },
    {
      "name": "Leonel",
      "company": "Amazon",
      "email": "leoenl@leo.com",
      "phone": "3122222222",
      "notes": "Notes....",
      "id": 3
    },
    {
      "name": "Camilo",
      "company": "AWS",
      "email": "email3@email3.com",
      "phone": "3254111",
      "notes": "More Notes....",
      "id": 4
    },
    {
      "name": "Maria",
      "company": "TECH",
      "email": "email@email.com",
      "phone": "3010101",
      "notes": "More more notes...",
      "id": 5
    }
  ]
}